aiogram_dialog_survey/__init__.py
aiogram_dialog_survey/entities/__pycache__/action_type.cpython-311.pyc
aiogram_dialog_survey/entities/__pycache__/button.cpython-311.pyc
aiogram_dialog_survey/entities/__pycache__/question.cpython-311.pyc
aiogram_dialog_survey/entities/action_type.py
aiogram_dialog_survey/entities/button.py
aiogram_dialog_survey/entities/question.py
aiogram_dialog_survey/handler.py
aiogram_dialog_survey/navigation_button.py
aiogram_dialog_survey/protocols/__pycache__/handler.cpython-311.pyc
aiogram_dialog_survey/protocols/__pycache__/navigation_button.cpython-311.pyc
aiogram_dialog_survey/protocols/__pycache__/state_manager.cpython-311.pyc
aiogram_dialog_survey/protocols/__pycache__/survey.cpython-311.pyc
aiogram_dialog_survey/protocols/__pycache__/widget.cpython-311.pyc
aiogram_dialog_survey/protocols/__pycache__/widget_factory.cpython-311.pyc
aiogram_dialog_survey/protocols/handler.py
aiogram_dialog_survey/protocols/navigation_button.py
aiogram_dialog_survey/protocols/state_manager.py
aiogram_dialog_survey/protocols/survey.py
aiogram_dialog_survey/protocols/widget.py
aiogram_dialog_survey/protocols/widget_factory.py
aiogram_dialog_survey/state.py
aiogram_dialog_survey/survey.py
aiogram_dialog_survey/triggers.py
aiogram_dialog_survey/widget_factory.py
aiogram_dialog_survey/widgets.py
aiogram_dialog_survey-0.3.2.dist-info/METADATA
aiogram_dialog_survey-0.3.2.dist-info/WHEEL
aiogram_dialog_survey-0.3.2.dist-info/RECORD
