Metadata-Version: 2.3
Name: aiogram-dialog-survey
Version: 0.3.2
Summary: Quick and easy creation of surveys, questionnaires, and forms using aiogram-dialog
License: Apache-2.0
Author: Pavel Danilevich
Author-email: danilevitch.pasha@yandex.ru
Requires-Python: >=3.9
Classifier: Intended Audience :: Developers
Classifier: License :: OSI Approved :: Apache Software License
Classifier: Operating System :: OS Independent
Classifier: Programming Language :: Python :: 3
Classifier: Programming Language :: Python :: 3.9
Classifier: Programming Language :: Python :: 3.10
Classifier: Programming Language :: Python :: 3.11
Classifier: Programming Language :: Python :: 3.12
Classifier: Programming Language :: Python :: 3.13
Requires-Dist: aiogram (>=3.14.0)
Requires-Dist: aiogram-dialog (>=2.3.1)
Project-URL: bug-tracker, https://github.com/pasha-danilevich/aiogram_dialog_survey/issues
Project-URL: homepage, https://github.com/pasha-danilevich/aiogram_dialog_survey
